traceable_agent.libs/libgcc_s-a3a07607.so.1
traceable_agent.libs/libstdc++-496613c0.so.6.0.32
traceableai/env.py
traceableai/custom_logger.py
traceableai/__init__.py
traceableai/version.py
traceableai/agent_init.py
traceableai/agent.py
traceableai/constants.py
traceableai/filter/_libtraceable.cpython-311-x86_64-linux-musl.so
traceableai/filter/_libtraceable.c
traceableai/filter/__init__.py
traceableai/filter/filter.py
traceableai/filter/traceable.py
traceableai/filter/_libtraceable.cpython-310-x86_64-linux-gnu.so
traceableai/filter/_libtraceable.cpython-312-x86_64-linux-musl.so
traceableai/filter/libtraceable.h.preprocessed
traceableai/filter/_libtraceable.o
traceableai/filter/_libtraceable.cpython-39-x86_64-linux-gnu.so
traceableai/filter/registry.py
traceableai/filter/_libtraceable.cpython-38-x86_64-linux-gnu.so
traceableai/instrumentation/__init__.py
traceableai/instrumentation/instrumentation_definitions.py
traceableai/instrumentation/botocore/__init__.py
traceableai/instrumentation/fast_api/__init__.py
traceableai/instrumentation/fast_api/fast_api_auto_instrumentation_compat.py
traceableai/instrumentation/aws_lambda/__init__.py
traceableai/instrumentation/postgresql/__init__.py
traceableai/instrumentation/boto/__init__.py
traceableai/instrumentation/grpc/__init__.py
traceableai/instrumentation/mysql/__init__.py
traceableai/instrumentation/aiohttp/__init__.py
traceableai/instrumentation/django/__init__.py
traceableai/instrumentation/django/django_auto_instrumentation_compat.py
traceableai/instrumentation/flask/__init__.py
traceableai/instrumentation/requests/__init__.py
traceableai/config/environment.py
traceableai/config/default.py
traceableai/config/__init__.py
traceableai/config/config_pb2.py
traceableai/config/config.py
traceableai/autoinstrumentation/__init__.py
traceableai/autoinstrumentation/sitecustomize.py
traceableai/autoinstrumentation/wrapper.py
traceable_agent-2.0.1.dist-info/top_level.txt
traceable_agent-2.0.1.dist-info/METADATA
traceable_agent-2.0.1.dist-info/entry_points.txt
traceable_agent-2.0.1.dist-info/WHEEL
traceable_agent-2.0.1.dist-info/RECORD
