Metadata-Version: 2.1
Name: traceable-agent
Version: 2.0.1
Summary: Traceable.ai Python Agent
Home-page: https://traceable.ai
Author: Traceable.ai
License: UNKNOWN
Platform: UNKNOWN
Classifier: Programming Language :: Python :: 3
Classifier: Operating System :: OS Independent
Requires-Python: >=3.8
